cmdmark/__init__.py
cmdmark/main.py
cmdmark-0.0.6.dist-info/LICENSE
cmdmark-0.0.6.dist-info/METADATA
cmdmark-0.0.6.dist-info/WHEEL
cmdmark-0.0.6.dist-info/entry_points.txt
cmdmark-0.0.6.dist-info/RECORD
