Metadata-Version: 2.3
Name: cmdmark
Version: 0.0.6
Summary: A CLI tool for managing commands like bookmarks
License: MIT
Author: Po-wei Huang
Author-email: abc1199281@gmail.com
Requires-Python: >=3.12
Classifier: License :: OSI Approved :: MIT License
Classifier: Programming Language :: Python :: 3
Classifier: Programming Language :: Python :: 3.12
Classifier: Programming Language :: Python :: 3.13
Provides-Extra: test
Requires-Dist: pyaml (>=25.5.0,<26.0.0)
Requires-Dist: pytest (>=8.3.5,<9.0.0) ; extra == "test"
Requires-Dist: pyyaml (>=6.0.2,<7.0.0)
Project-URL: Homepage, https://github.com/abc1199281/cmdmark
